{
    "Z_300_399_Unique exceptions": {
        "356": {
            "content": [
                "Z356. †Z356. ", 
                "Unique survivor.", 
                " Only one person left from destruction of his community. India:\r\n*Thompson-Balys; Hawaii: Beckwith Myth 135, 443f., 449; Marquesas: Handy 77;\r\nEaster Island: Métraux Ethnology 71; Tuamotu: Stimson MS (z-G. 13/203); Tahiti: Henry Ancient Tahiti (Honolulu, 1928) 246."
            ], 
            "child": []
        }, 
        "313": {
            "content": [
                "Z313. †Z313. ", 
                "Vulnerability only by one person.", 
                " Irish myth: *Cross; Icelandic: *Boberg; India:\r\nThompson-Balys; Hindu: Keith 153."
            ], 
            "child": [
                [
                    "Z313.1. †Z313.1. ", 
                    "Only one person can overtake hero.", 
                    " Maori: Beckwith Myth 231."
                ]
            ]
        }, 
        "312": {
            "content": [
                "Z312. †Z312. ", 
                "Unique deadly weapon.", 
                " Only one thing will kill a certain man. *Dh\r\nII 211; *Wesselski Archiv Orientální II 430; Penzer VIII 109 n. 3; R. M. Meyer\r\nArchiv f. Religionsgeschichte (1907) 93ff. -- Irish: MacCulloch Celtic 151,\r\n*Cross; Icelandic: De la Saussaye 154, 156, *Boberg; N. A. Indian: *Thompson\r\nTales 357 n. 287g; Africa (Cameroon): Ittman 77, (Swahili): Steere 441."
            ], 
            "child": [
                [
                    "Z312.1. †Z312.1. ", 
                    "Person can be killed only by red-hot spits being thrust\r\nthrough soles of his feet.", 
                    " Irish myth:\r\n*Cross."
                ], 
                [
                    "Z312.2. †Z312.2. ", 
                    "Giant ogre can be killed only with iron club he carries\r\n(with own sword).", 
                    " Irish myth: *Cross;\r\nIcelandic: *Boberg."
                ], 
                [
                    "Z312.3. †Z312.3. ", 
                    "Unique source of weakness.", 
                    " Hawaii: Beckwith Myth 204."
                ], 
                [
                    "Z312.4. †Z312.4. ", 
                    "Unique bait for fish.", 
                    "\r\nHawaii: Beckwith Myth 216."
                ]
            ]
        }, 
        "311": {
            "content": [
                "Z311. †Z311. ", 
                "Achilles heel.", 
                " Invulnerability except in one spot. **DeCock Studien\r\n153ff.--Irish myth: *Cross; Welsh: MacCulloch Celtic 97; Icelandic: *Boberg;\r\nNorse: De la Saussaye 144, Von Sydow Fåvne 27ff.; French Canadian: Barbeau JAFL\r\nXXIX 11; Greek: *Basset RTP XXV 124 n. 1, Frazer Apollodorus II 60 n. 2, 214 n.\r\n1; Jewish: *Neuman; Hindu: Keith 125, Penzer I 127; Siberian: Holmberg Siberian\r\n389; Eskimo (Mackenzie Area): Jenness 67; N. A. Indian: *Thompson Tales 345 n.\r\n246; Africa: Werner African 236, (Fang): Trilles 202."
            ], 
            "child": [
                [
                    "Z311.1. †Z311.1. ", 
                    "Left eye only vulnerable spot.", 
                    " Irish myth: Cross."
                ], 
                [
                    "Z311.2. †Z311.2. ", 
                    "Spot below right ear only vulnerable one.", 
                    " Irish myth: Cross."
                ], 
                [
                    "Z311.3. †Z311.3. ", 
                    "Leprosy cured by holy water except on thumb.", 
                    " India: Thompson-Balys."
                ], 
                [
                    "Z311.4. †Z311.4. ", 
                    "Man can be injured only in armpits.", 
                    " India: Thompson-Balys."
                ]
            ]
        }, 
        "310": {
            "content": [
                "Z310. ", 
                null, 
                null
            ], 
            "child": []
        }, 
        "300": {
            "content": [
                "Z300. ", 
                null, 
                null
            ], 
            "child": []
        }, 
        "316": {
            "content": [
                "Z316. †Z316. ", 
                "Only one way to besiege certain city.", 
                " Jewish: Neuman."
            ], 
            "child": []
        }, 
        "315": {
            "content": [
                "Z315. †Z315. ", 
                "Ogre vulnerable only when his face is turned away when he\r\nis struck.", 
                " India: Thompson-Balys."
            ], 
            "child": []
        }, 
        "314": {
            "content": [
                "Z314. †Z314. ", 
                "Sword which will break in only one peril: this known only\r\nto the maker of the sword.", 
                " Gaster FL II\r\n57; Nutt Holy Grail 11."
            ], 
            "child": []
        }, 
        "322": {
            "content": [
                "Z322. †Z322. ", 
                "Only one ferule fits certain staff.", 
                " Irish myth: Cross."
            ], 
            "child": []
        }, 
        "323": {
            "content": [
                "Z323. †Z323. ", 
                "Vessel from which nothing can be drunk save through certain\r\ntube.", 
                " Irish myth: Cross."
            ], 
            "child": []
        }, 
        "320": {
            "content": [
                "Z320. ", 
                null, 
                null
            ], 
            "child": []
        }, 
        "321": {
            "content": [
                "Z321. †Z321. ", 
                "Ring fits only one person.", 
                " Irish myth: Cross."
            ], 
            "child": []
        }, 
        "352": {
            "content": [
                "Z352. †Z352. ", 
                "All trees except aspen refuse to make Christ’s cross.", 
                " Dh II 209; North Carolina: Brown Collection I 635."
            ], 
            "child": []
        }, 
        "351": {
            "content": [
                "Z351. †Z351. ", 
                "Only one person refuses to weep at hero‘s death.", 
                " Icelandic: Boberg."
            ], 
            "child": []
        }, 
        "350": {
            "content": [
                "Z350. ", 
                null, 
                null
            ], 
            "child": []
        }, 
        "355": {
            "content": [
                "Z355. †Z355. ", 
                "All snakes but one placated by music.", 
                " In snake den prisoner\r\nfails to placate one snake and loses his life. Hdwb. d. Märchens I 437a."
            ], 
            "child": []
        }
    }
}